enzymeml/__init__.py
enzymeml/enzymeml.py
enzymeml/enzymemlkey.py
enzymeml/ontologymanager.py
enzymeml/tables.py
python_enzymeml-1.0.0.dist-info/LICENSE
python_enzymeml-1.0.0.dist-info/METADATA
python_enzymeml-1.0.0.dist-info/WHEEL
python_enzymeml-1.0.0.dist-info/top_level.txt
python_enzymeml-1.0.0.dist-info/RECORD
